chromaterm/__init__.py
chromaterm/__version__.py
chromaterm/cli.py
chromaterm/core.py
chromaterm/default_config.py
chromaterm/pcre.py
chromaterm/platform/__init__.py
chromaterm/platform/unix.py
chromaterm/platform/tests/__init__.py
chromaterm/platform/tests/test_unix.py
chromaterm/tests/__init__.py
chromaterm/tests/conftest.py
chromaterm/tests/test___init__.py
chromaterm/tests/test_default_config.py
chromaterm/tests/test_pcre.py
chromaterm2-2.0.1.dist-info/licenses/LICENSE
chromaterm2-2.0.1.dist-info/METADATA
chromaterm2-2.0.1.dist-info/WHEEL
chromaterm2-2.0.1.dist-info/entry_points.txt
chromaterm2-2.0.1.dist-info/top_level.txt
chromaterm2-2.0.1.dist-info/RECORD
