Metadata-Version: 2.4
Name: chromaterm2
Version: 2.0.1
Summary: Color your Terminal with Regex! (Maintained fork of ChromaTerm)
Home-page: https://github.com/rgcr/ChromaTerm2
Author: rgcr
Author-email: rgcr <roger.dev@pm.me>
Maintainer-email: rgcr <roger.dev@pm.me>
License: MIT
Project-URL: Homepage, https://github.com/rgcr/ChromaTerm2
Project-URL: Repository, https://github.com/rgcr/ChromaTerm2.git
Project-URL: Issues, https://github.com/rgcr/ChromaTerm2/issues
Project-URL: Changelog, https://github.com/rgcr/ChromaTerm2/blob/main/CHANGELOG.md
Keywords: terminal,color,regex,highlighting,cli
Classifier: Intended Audience :: Information Technology
Classifier: Intended Audience :: System Administrators
Classifier: Intended Audience :: Telecommunications Industry
Classifier: License :: OSI Approved :: MIT License
Classifier: Programming Language :: Python :: 3
Classifier: Programming Language :: Python :: 3.9
Classifier: Programming Language :: Python :: 3.10
Classifier: Programming Language :: Python :: 3.11
Classifier: Programming Language :: Python :: 3.12
Classifier: Programming Language :: Python :: 3.13
Classifier: Topic :: Terminals
Classifier: Topic :: Utilities
Requires-Python: >=3.9.0
License-File: LICENSE
Requires-Dist: psutil
Requires-Dist: pyyaml>=5.1
Dynamic: author
Dynamic: home-page
Dynamic: license-file
Dynamic: requires-python
